data_loader/__init__.py
data_loader/data_validation.py
data_loader/generic_data_loader.py
data_loader/sqlite_adapter.py
evolvishub_dataloader-1.0.0.dist-info/licenses/LICENSE
utils/config_manager.py
utils/logger.py
evolvishub_dataloader-1.0.0.dist-info/METADATA
evolvishub_dataloader-1.0.0.dist-info/WHEEL
evolvishub_dataloader-1.0.0.dist-info/top_level.txt
evolvishub_dataloader-1.0.0.dist-info/RECORD
