Metadata-Version: 2.4
Name: evolvishub-dataloader
Version: 1.0.0
Summary: A comprehensive data loading framework for Excel, CSV, and JSON files with async support and data validation
Author-email: EvolvisAI <info@evolvis.ai>
Maintainer-email: EvolvisAI <info@evolvis.ai>
License: MIT License
Project-URL: Homepage, https://github.com/evolvisai/evolvishub-dataloader
Project-URL: Repository, https://github.com/evolvisai/evolvishub-dataloader
Project-URL: Documentation, https://github.com/evolvisai/evolvishub-dataloader#readme
Project-URL: Bug Tracker, https://github.com/evolvisai/evolvishub-dataloader/issues
Keywords: data-loader,excel,csv,json,async,data-validation,sqlite,etl,data-processing
Classifier: Development Status :: 5 - Production/Stable
Classifier: Intended Audience :: Developers
Classifier: License :: OSI Approved :: MIT License
Classifier: Operating System :: OS Independent
Classifier: Programming Language :: Python :: 3
Classifier: Programming Language :: Python :: 3.8
Classifier: Programming Language :: Python :: 3.9
Classifier: Programming Language :: Python :: 3.10
Classifier: Programming Language :: Python :: 3.11
Classifier: Programming Language :: Python :: 3.12
Classifier: Topic :: Software Development :: Libraries :: Python Modules
Classifier: Topic :: Database
Classifier: Topic :: Office/Business
Classifier: Topic :: Scientific/Engineering :: Information Analysis
Requires-Python: >=3.8
License-File: LICENSE
Requires-Dist: pandas>=1.5.0
Requires-Dist: openpyxl>=3.0.0
Requires-Dist: xlrd>=2.0.0
Requires-Dist: PyYAML>=6.0
Requires-Dist: aiofiles>=23.0.0
Provides-Extra: test
Requires-Dist: pytest>=7.0.0; extra == "test"
Requires-Dist: pytest-asyncio>=0.21.0; extra == "test"
Requires-Dist: pytest-cov>=4.0.0; extra == "test"
Requires-Dist: pytest-mock>=3.10.0; extra == "test"
Requires-Dist: xlwt>=1.3.0; extra == "test"
Provides-Extra: dev
Requires-Dist: black>=23.0.0; extra == "dev"
Requires-Dist: isort>=5.12.0; extra == "dev"
Requires-Dist: flake8>=6.0.0; extra == "dev"
Requires-Dist: mypy>=1.0.0; extra == "dev"
Dynamic: license-file
